LICENSE
README.md
setup.py
deepvoxnet2/__init__.py
deepvoxnet2.egg-info/PKG-INFO
deepvoxnet2.egg-info/SOURCES.txt
deepvoxnet2.egg-info/dependency_links.txt
deepvoxnet2.egg-info/not-zip-safe
deepvoxnet2.egg-info/requires.txt
deepvoxnet2.egg-info/top_level.txt
deepvoxnet2/analysis/__init__.py
deepvoxnet2/analysis/analysis.py
deepvoxnet2/analysis/data.py
deepvoxnet2/analysis/plotting.py
deepvoxnet2/backwards_compatibility/__init__.py
deepvoxnet2/backwards_compatibility/losses.py
deepvoxnet2/backwards_compatibility/metrics.py
deepvoxnet2/components/__init__.py
deepvoxnet2/components/creator.py
deepvoxnet2/components/cupy_transformers.py
deepvoxnet2/components/mirc.py
deepvoxnet2/components/model.py
deepvoxnet2/components/sample.py
deepvoxnet2/components/sampler.py
deepvoxnet2/components/transformers.py
deepvoxnet2/factories/__init__.py
deepvoxnet2/factories/directory_structure.py
deepvoxnet2/keras/__init__.py
deepvoxnet2/keras/callbacks.py
deepvoxnet2/keras/losses.py
deepvoxnet2/keras/metrics.py
deepvoxnet2/keras/optimizers.py
deepvoxnet2/keras/models/__init__.py
deepvoxnet2/keras/models/deepmedic_generalized.py
deepvoxnet2/keras/models/deepmedic_generalized_v2.py
deepvoxnet2/keras/models/unet_generalized.py
deepvoxnet2/keras/models/unet_generalized_v2.py
deepvoxnet2/keras/models/unet_generalized_v3.py
deepvoxnet2/keras/models/unet_generalized_v4.py
deepvoxnet2/utilities/__init__.py
deepvoxnet2/utilities/calculate_gpu_memory.py
deepvoxnet2/utilities/conversions.py
deepvoxnet2/utilities/drawing.py
deepvoxnet2/utilities/transformations.py