Metadata-Version: 2.4
Name: deepvoxnet2
Version: 2.20.2
Summary: Yet another CNN framework: From pre- to postprocessing and keeping track of the spatial origin of the data.
Home-page: https://github.com/JeroenBertels/deepvoxnet2
Author: Jeroen Bertels
Author-email: jeroen.bertels@gmail.com
Classifier: Programming Language :: Python :: 3
Classifier: License :: OSI Approved :: GNU Lesser General Public License v3 or later (LGPLv3+)
Classifier: Operating System :: OS Independent
Requires-Python: >=3.12, <3.14
License-File: LICENSE
Requires-Dist: tensorflow[and-cuda]==2.20.0
Requires-Dist: nibabel==5.3.2
Requires-Dist: transforms3d==0.4.2
Requires-Dist: pandas==2.3.3
Requires-Dist: scikit-learn==1.7.2
Requires-Dist: cupy-cuda12x==13.6.0
Requires-Dist: pydot==4.0.1
Requires-Dist: matplotlib==3.10.7
Requires-Dist: numba==0.62.1
Provides-Extra: full
Requires-Dist: tensorflow-probability; extra == "full"
Requires-Dist: simpleitk-simpleelastix; extra == "full"
Requires-Dist: pydicom; extra == "full"
Requires-Dist: numba; extra == "full"
Requires-Dist: seaborn; extra == "full"
Requires-Dist: pymirc; extra == "full"
Dynamic: author
Dynamic: author-email
Dynamic: classifier
Dynamic: description
Dynamic: description-content-type
Dynamic: home-page
Dynamic: license-file
Dynamic: provides-extra
Dynamic: requires-dist
Dynamic: requires-python
Dynamic: summary
